tgedr/ds/__init__.py
tgedr/ds/fs_utils.py
tgedr/ds/nlp_utils.py
tgedr/ds/pytorch/utils.py
tgedr/ds/sources/reddit.py
tgedr/ds/sources/source.py
tgedr_ds-0.0.7.dist-info/METADATA
tgedr_ds-0.0.7.dist-info/WHEEL
tgedr_ds-0.0.7.dist-info/licenses/LICENSE
tgedr_ds-0.0.7.dist-info/RECORD
